Metadata-Version: 2.1
Name: makeReact
Version: 0.0.5
Summary: makeReact is a python package which helps react and react-native developer to speed-up their develoment process.
Home-page: UNKNOWN
Author: Hur Ali
Author-email: hurali97@gmail.com
License: UNKNOWN
Platform: UNKNOWN
